js_lib_tabulator/__init__.py
js_lib_tabulator/apps.py
js_lib_tabulator/static/tabulator/css/tabulator.css
js_lib_tabulator/static/tabulator/css/tabulator.css.map
js_lib_tabulator/static/tabulator/css/tabulator.min.css
js_lib_tabulator/static/tabulator/css/tabulator.min.css.map
js_lib_tabulator/static/tabulator/css/tabulator_bootstrap3.css
js_lib_tabulator/static/tabulator/css/tabulator_bootstrap3.css.map
js_lib_tabulator/static/tabulator/css/tabulator_bootstrap3.min.css
js_lib_tabulator/static/tabulator/css/tabulator_bootstrap3.min.css.map
js_lib_tabulator/static/tabulator/css/tabulator_bootstrap4.css
js_lib_tabulator/static/tabulator/css/tabulator_bootstrap4.css.map
js_lib_tabulator/static/tabulator/css/tabulator_bootstrap4.min.css
js_lib_tabulator/static/tabulator/css/tabulator_bootstrap4.min.css.map
js_lib_tabulator/static/tabulator/css/tabulator_bootstrap5.css
js_lib_tabulator/static/tabulator/css/tabulator_bootstrap5.css.map
js_lib_tabulator/static/tabulator/css/tabulator_bootstrap5.min.css
js_lib_tabulator/static/tabulator/css/tabulator_bootstrap5.min.css.map
js_lib_tabulator/static/tabulator/css/tabulator_bulma.css
js_lib_tabulator/static/tabulator/css/tabulator_bulma.css.map
js_lib_tabulator/static/tabulator/css/tabulator_bulma.min.css
js_lib_tabulator/static/tabulator/css/tabulator_bulma.min.css.map
js_lib_tabulator/static/tabulator/css/tabulator_materialize.css
js_lib_tabulator/static/tabulator/css/tabulator_materialize.css.map
js_lib_tabulator/static/tabulator/css/tabulator_materialize.min.css
js_lib_tabulator/static/tabulator/css/tabulator_materialize.min.css.map
js_lib_tabulator/static/tabulator/css/tabulator_midnight.css
js_lib_tabulator/static/tabulator/css/tabulator_midnight.css.map
js_lib_tabulator/static/tabulator/css/tabulator_midnight.min.css
js_lib_tabulator/static/tabulator/css/tabulator_midnight.min.css.map
js_lib_tabulator/static/tabulator/css/tabulator_modern.css
js_lib_tabulator/static/tabulator/css/tabulator_modern.css.map
django_js_lib_tabulator-6.3.1.1.dist-info/LICENSE.txt
django_js_lib_tabulator-6.3.1.1.dist-info/WHEEL
django_js_lib_tabulator-6.3.1.1.dist-info/METADATA
django_js_lib_tabulator-6.3.1.1.dist-info/RECORD
