Metadata-Version: 2.3
Name: django-js-lib-tabulator
Version: 6.3.1.1
Summary: Tabulator for Django
Classifier: License :: OSI Approved :: MIT License
